emm/__init__.py
emm/parameters.py
emm/resources.py
emm/version.py
emm/aggregation/__init__.py
emm/aggregation/base_entity_aggregation.py
emm/aggregation/pandas_entity_aggregation.py
emm/aggregation/spark_entity_aggregation.py
emm/base/__init__.py
emm/base/module.py
emm/base/pipeline.py
emm/data/README.md
emm/data/__init__.py
emm/data/create_data.py
emm/data/negative_data_creation.py
emm/data/noiser.py
emm/data/prepare_name_pairs.py
emm/data/unittest_sample_namepairs.csv.gz
emm/features/__init__.py
emm/features/base_feature_extractor.py
emm/features/features_extra.py
emm/features/features_lef.py
emm/features/features_name.py
emm/features/features_rank.py
emm/features/features_vocabulary.py
emm/features/pandas_feature_extractor.py
emm/helper/__init__.py
emm/helper/blocking_functions.py
emm/helper/custom_path.py
emm/helper/io.py
emm/helper/sklearn_pipeline.py
emm/helper/spark_custom_reader_writer.py
emm/helper/spark_ml_pipeline.py
emm/helper/spark_utils.py
emm/helper/util.py
emm/indexing/__init__.py
emm/indexing/base_indexer.py
emm/indexing/pandas_candidate_selection.py
emm/indexing/pandas_cos_sim_matcher.py
emm/indexing/pandas_naive_indexer.py
emm/indexing/pandas_normalized_tfidf.py
emm/indexing/pandas_sni.py
emm/indexing/spark_candidate_selection.py
emm/indexing/spark_character_tokenizer.py
emm/indexing/spark_cos_sim_matcher.py
emm/indexing/spark_indexing_utils.py
emm/indexing/spark_normalized_tfidf.py
emm/indexing/spark_sni.py
emm/indexing/spark_word_tokenizer.py
emm/loggers/__init__.py
emm/loggers/logger.py
emm/loggers/timer.py
emm/pipeline/__init__.py
emm/pipeline/base_entity_matching.py
emm/pipeline/pandas_entity_matching.py
emm/pipeline/spark_entity_matching.py
emm/preprocessing/__init__.py
emm/preprocessing/abbreviation_util.py
emm/preprocessing/base_name_preprocessor.py
emm/preprocessing/functions.py
emm/preprocessing/pandas_functions.py
emm/preprocessing/pandas_preprocessor.py
emm/preprocessing/spark_functions.py
emm/preprocessing/spark_preprocessor.py
emm-2.1.9.dist-info/LICENSE
emm-2.1.9.dist-info/METADATA
emm-2.1.9.dist-info/NOTICE
emm-2.1.9.dist-info/WHEEL
emm-2.1.9.dist-info/top_level.txt
emm-2.1.9.dist-info/RECORD
