Metadata-Version: 2.2
Name: emm
Version: 2.1.9
Summary: Entity Matching Model package
Author-email: Max Baak <max.baak@ing.com>, Stephane Collot <stephane.collot@gmail.com>, Apoorva Mahajan <apoorva.mahajan@ing.com>, Tomasz Waleń <tomasz.walen@ing.com>, Simon Brugman <simon.brugman@ing.com>
Requires-Python: >=3.8
License-File: LICENSE
License-File: NOTICE
Requires-Dist: numpy>=1.20.1
Requires-Dist: scipy
Requires-Dist: scikit-learn<1.6.0
Requires-Dist: pandas!=1.5.0,>=1.1.0
Requires-Dist: jinja2
Requires-Dist: rapidfuzz<3.0.0
Requires-Dist: regex
Requires-Dist: urllib3
Requires-Dist: recordlinkage
Requires-Dist: cleanco>=2.2
Requires-Dist: xgboost
Requires-Dist: sparse-dot-topn>=1.1.1
Requires-Dist: joblib
Requires-Dist: pyarrow>=6.0.1
Requires-Dist: requests
Requires-Dist: unidecode
Provides-Extra: spark
Requires-Dist: pyspark>=3.1; python_version <= "3.11" and extra == "spark"
Provides-Extra: dev
Requires-Dist: pre-commit; extra == "dev"
Requires-Dist: gitpython; extra == "dev"
Requires-Dist: nbconvert; extra == "dev"
Requires-Dist: jupyter_client>=5.2.3; extra == "dev"
Requires-Dist: ipykernel>=5.1.3; extra == "dev"
Requires-Dist: matplotlib; extra == "dev"
Requires-Dist: pygments; extra == "dev"
Requires-Dist: pandoc; extra == "dev"
Requires-Dist: pympler; extra == "dev"
Provides-Extra: test
Requires-Dist: pytest; extra == "test"
Requires-Dist: pytest-ordering; extra == "test"
Requires-Dist: virtualenv; extra == "test"
Provides-Extra: test-cov
Requires-Dist: coverage; extra == "test-cov"
Requires-Dist: pytest-cov; extra == "test-cov"
Provides-Extra: test-bench
Requires-Dist: pytest-benchmark; extra == "test-bench"
Provides-Extra: test-notebook
Requires-Dist: pytest-notebook>=0.6.1; extra == "test-notebook"
Requires-Dist: ipykernel>=5.1.3; extra == "test-notebook"
Requires-Dist: matplotlib; extra == "test-notebook"
Requires-Dist: nbdime<4; extra == "test-notebook"
Provides-Extra: doc
Requires-Dist: matplotlib; extra == "doc"
Requires-Dist: seaborn; extra == "doc"
Requires-Dist: sphinx; extra == "doc"
Requires-Dist: sphinx-material; extra == "doc"
Requires-Dist: furo; extra == "doc"
Requires-Dist: sphinx-copybutton; extra == "doc"
Requires-Dist: sphinx-autodoc-typehints; extra == "doc"
Requires-Dist: jupyter_contrib_nbextensions; extra == "doc"
Requires-Dist: nbstripout; extra == "doc"
Requires-Dist: nbsphinx; extra == "doc"
Requires-Dist: nbsphinx-link; extra == "doc"
Requires-Dist: ipywidgets; extra == "doc"
Requires-Dist: jinja2; extra == "doc"
Requires-Dist: jinja-cli; extra == "doc"
Requires-Dist: markupsafe; extra == "doc"
Requires-Dist: pandoc; extra == "doc"
Requires-Dist: jupyter_client>=5.2.3; extra == "doc"
Requires-Dist: myst_parser; extra == "doc"
